ctlsettings/__init__.py
ctlsettings/context_processors.py
ctlsettings/production.py
ctlsettings/shared.py
ctlsettings/staging.py
ctlsettings/storages.py
ctlsettings/templates/ctlsettings/sentry_js.html
ctlsettings-0.4.6.dist-info/licenses/LICENSE
ctlsettings-0.4.6.dist-info/METADATA
ctlsettings-0.4.6.dist-info/WHEEL
ctlsettings-0.4.6.dist-info/top_level.txt
ctlsettings-0.4.6.dist-info/RECORD
