Metadata-Version: 2.4
Name: ctlsettings
Version: 0.4.6
Summary: Columbia CTL common Django base settings
Home-page: https://github.com/ccnmtl/ctlsettings
Author: Columbia University Center for Teaching and Learning
Author-email: ctl-dev@columbia.edu
License: GPL-3.0-or-later
Platform: any
License-File: LICENSE
Requires-Dist: django-cas-ng
Requires-Dist: django-debug-toolbar
Requires-Dist: django-smoketest
Requires-Dist: django-extensions
Requires-Dist: sentry-sdk
Requires-Dist: django-storages
Requires-Dist: boto3
Requires-Dist: requests
Requires-Dist: gunicorn
Requires-Dist: django-impersonate
Dynamic: author
Dynamic: author-email
Dynamic: description
Dynamic: description-content-type
Dynamic: home-page
Dynamic: license
Dynamic: license-file
Dynamic: platform
Dynamic: requires-dist
Dynamic: summary
